djspa/__init__.py
djspa/exceptions.py
djspa/urls.py
djspa/views.py
djspa/static/djspa/imgs/pagest.png
djspa/static/djspa/imgs/pagest.svg
djspa/static/djspa/js/djspa.js
djspa/templates/djspa_head.html
djspa/templates/djspa_pages.html
djspa-1.0.1.dist-info/LICENSE
djspa-1.0.1.dist-info/METADATA
djspa-1.0.1.dist-info/WHEEL
djspa-1.0.1.dist-info/top_level.txt
djspa-1.0.1.dist-info/RECORD
