Metadata-Version: 2.1
Name: djspa
Version: 1.0.1
Summary: Django addon for a single page application with dynamically loaded pages
Home-page: https://git.voltane.eu/voltane/pypi/djspa
Author: Manuel Stingl
Author-email: opensource@voltane.eu
License: GNU GPLv3
Platform: UNKNOWN
Classifier: Programming Language :: Python :: 3
Classifier: License :: OSI Approved :: GNU General Public License v3 or later (GPLv3+)
Classifier: Operating System :: OS Independent
Classifier: Framework :: Django
Classifier: Framework :: Django :: 2.0
Classifier: Framework :: Django :: 2.1
Classifier: Framework :: Django :: 2.2
Classifier: Framework :: Django :: 3.0
Requires-Python: >=3.6
Requires-Dist: django (>=2.0)
